Image_Processing/Dehazing.py
Image_Processing/__init__.py
Image_Processing/utils.py
Machine_Learning/__init__.py
Machine_Learning/adaboost.py
Machine_Learning/decision_stamp.py
Machine_Learning/utils.py
Machine_Learning/test/__init__.py
Machine_Learning/test/adaboost_test.py
Machine_Learning/test/decision_stamp_test.py
Algorithms_abhay-0.0.1.dist-info/LICENSE
Algorithms_abhay-0.0.1.dist-info/METADATA
Algorithms_abhay-0.0.1.dist-info/WHEEL
Algorithms_abhay-0.0.1.dist-info/top_level.txt
Algorithms_abhay-0.0.1.dist-info/RECORD
